faxplus/__init__.py
faxplus/api_client.py
faxplus/configuration.py
faxplus/rest.py
faxplus/api/__init__.py
faxplus/api/accounts_api.py
faxplus/api/faxes_api.py
faxplus/api/files_api.py
faxplus/api/numbers_api.py
faxplus/api/outbox_api.py
faxplus/api/shop_api.py
faxplus/api/webhooks_api.py
faxplus/models/__init__.py
faxplus/models/account.py
faxplus/models/account_data.py
faxplus/models/account_list.py
faxplus/models/account_notifications.py
faxplus/models/account_notifications_blacklist.py
faxplus/models/account_notifications_email_settings.py
faxplus/models/account_notifications_email_settings_attachments.py
faxplus/models/account_notifications_language.py
faxplus/models/account_notifications_push_settings.py
faxplus/models/account_notifications_settings.py
faxplus/models/account_notifications_slack_settings.py
faxplus/models/account_notifications_sms_settings.py
faxplus/models/account_settings.py
faxplus/models/account_settings_send_fax.py
faxplus/models/account_status.py
faxplus/models/account_type.py
faxplus/models/available_number.py
faxplus/models/available_number_item.py
faxplus/models/available_number_item_geographic_area.py
faxplus/models/available_number_list.py
faxplus/models/balance.py
faxplus/models/binary.py
faxplus/models/cover_page_flags.py
faxplus/models/error.py
faxplus/models/fax.py
faxplus/models/fax_category.py
faxplus/models/fax_cost_details.py
faxplus/models/fax_cover_page.py
faxplus/models/fax_direction.py
faxplus/models/fax_list.py
faxplus/models/fax_list_data.py
faxplus/models/fax_status.py
faxplus/models/file.py
faxplus/models/file_path.py
faxplus/models/file_type.py
faxplus/models/member_detail.py
faxplus/models/number.py
faxplus/models/number_area.py
faxplus/models/number_area_list.py
faxplus/models/number_available_country.py
faxplus/models/number_list.py
faxplus/models/number_notifications.py
faxplus/models/number_status.py
faxplus/models/numbers_available_countries.py
faxplus/models/outbox.py
faxplus/models/outbox_comment.py
faxplus_api-3.0.5.dist-info/METADATA
faxplus_api-3.0.5.dist-info/WHEEL
faxplus_api-3.0.5.dist-info/top_level.txt
faxplus_api-3.0.5.dist-info/RECORD
