Metadata-Version: 2.1
Name: faxplus-api
Version: 3.0.5
Summary: Fax.Plus REST API
Home-page: https://github.com/alohi/faxplus-python
Author: Alohi SA
Author-email: info@fax.plus
Keywords: Swagger,Fax.Plus REST API
Requires-Dist: urllib3 >=1.15
Requires-Dist: six >=1.10
Requires-Dist: certifi
Requires-Dist: python-dateutil
